needlehaystack/__init__.py
needlehaystack/llm_multi_needle_haystack_tester.py
needlehaystack/llm_needle_haystack_tester.py
needlehaystack/run.py
needlehaystack/PaulGrahamEssays/addiction.txt
needlehaystack/PaulGrahamEssays/aord.txt
needlehaystack/PaulGrahamEssays/apple.txt
needlehaystack/PaulGrahamEssays/avg.txt
needlehaystack/PaulGrahamEssays/before.txt
needlehaystack/PaulGrahamEssays/bias.txt
needlehaystack/PaulGrahamEssays/boss.txt
needlehaystack/PaulGrahamEssays/copy.txt
needlehaystack/PaulGrahamEssays/corpdev.txt
needlehaystack/PaulGrahamEssays/desres.txt
needlehaystack/PaulGrahamEssays/diff.txt
needlehaystack/PaulGrahamEssays/ecw.txt
needlehaystack/PaulGrahamEssays/founders.txt
needlehaystack/PaulGrahamEssays/foundervisa.txt
needlehaystack/PaulGrahamEssays/gap.txt
needlehaystack/PaulGrahamEssays/gba.txt
needlehaystack/PaulGrahamEssays/gh.txt
needlehaystack/PaulGrahamEssays/goodtaste.txt
needlehaystack/PaulGrahamEssays/hubs.txt
needlehaystack/PaulGrahamEssays/iflisp.txt
needlehaystack/PaulGrahamEssays/island.txt
needlehaystack/PaulGrahamEssays/know.txt
needlehaystack/PaulGrahamEssays/langdes.txt
needlehaystack/PaulGrahamEssays/laundry.txt
needlehaystack/PaulGrahamEssays/love.txt
needlehaystack/PaulGrahamEssays/mod.txt
needlehaystack/PaulGrahamEssays/newideas.txt
needlehaystack/PaulGrahamEssays/nft.txt
needlehaystack/PaulGrahamEssays/philosophy.txt
needlehaystack/PaulGrahamEssays/popular.txt
needlehaystack/PaulGrahamEssays/pow.txt
needlehaystack/PaulGrahamEssays/rootsoflisp.txt
needlehaystack/PaulGrahamEssays/rss.txt
needlehaystack/PaulGrahamEssays/siliconvalley.txt
needlehaystack/PaulGrahamEssays/startuplessons.txt
needlehaystack/PaulGrahamEssays/submarine.txt
needlehaystack/PaulGrahamEssays/sun.txt
needlehaystack/PaulGrahamEssays/superangels.txt
needlehaystack/PaulGrahamEssays/todo.txt
needlehaystack/PaulGrahamEssays/unions.txt
needlehaystack/PaulGrahamEssays/useful.txt
needlehaystack/PaulGrahamEssays/vb.txt
needlehaystack/PaulGrahamEssays/vcsqueeze.txt
needlehaystack-0.1.0.dist-info/LICENSE.txt
needlehaystack-0.1.0.dist-info/METADATA
needlehaystack-0.1.0.dist-info/WHEEL
needlehaystack-0.1.0.dist-info/entry_points.txt
needlehaystack-0.1.0.dist-info/top_level.txt
needlehaystack-0.1.0.dist-info/RECORD
