Metadata-Version: 2.1
Name: needlehaystack
Version: 0.1.0
Summary: Doing simple retrieval from LLM models at various context lengths to measure accuracy.
Home-page: https://github.com/gkamradt/LLMTest_NeedleInAHaystack
Author: Greg Kamradt
Author-email: greg@gregkamradt.com
Requires-Python: >=3.6
License-File: LICENSE.txt
Requires-Dist: aiohttp ==3.9.1
Requires-Dist: aiosignal ==1.3.1
Requires-Dist: annotated-types ==0.6.0
Requires-Dist: anthropic >=0.7.5
Requires-Dist: anyio ==3.7.1
Requires-Dist: attrs ==23.1.0
Requires-Dist: certifi ==2023.11.17
Requires-Dist: charset-normalizer ==3.3.2
Requires-Dist: dataclasses-json ==0.6.3
Requires-Dist: distro ==1.8.0
Requires-Dist: filelock ==3.13.1
Requires-Dist: frozenlist ==1.4.0
Requires-Dist: fsspec ==2023.10.0
Requires-Dist: h11 ==0.14.0
Requires-Dist: httpcore ==1.0.2
Requires-Dist: httpx ==0.25.2
Requires-Dist: huggingface-hub ==0.19.4
Requires-Dist: idna ==3.6
Requires-Dist: jsonargparse ==4.27.5
Requires-Dist: jsonpatch ==1.33
Requires-Dist: jsonpointer ==2.4
Requires-Dist: langchain ==0.1.9
Requires-Dist: langchain-community >=0.0.24
Requires-Dist: langchain-core ==0.1.26
Requires-Dist: langsmith >=0.1.8
Requires-Dist: langchain-openai
Requires-Dist: langchain-anthropic
Requires-Dist: marshmallow ==3.20.1
Requires-Dist: multidict ==6.0.4
Requires-Dist: mypy-extensions ==1.0.0
Requires-Dist: numpy ==1.26.2
Requires-Dist: openai >=1.3.5
Requires-Dist: packaging ==23.2
Requires-Dist: pydantic ==2.5.2
Requires-Dist: pydantic-core ==2.14.5
Requires-Dist: python-dotenv ==1.0.0
Requires-Dist: PyYAML ==6.0.1
Requires-Dist: regex ==2023.10.3
Requires-Dist: requests ==2.31.0
Requires-Dist: sniffio ==1.3.0
Requires-Dist: SQLAlchemy ==2.0.23
Requires-Dist: tenacity ==8.2.3
Requires-Dist: tiktoken >=0.5.1
Requires-Dist: tokenizers ==0.15.0
Requires-Dist: tqdm ==4.66.1
Requires-Dist: typing-inspect ==0.9.0
Requires-Dist: typing-extensions ==4.8.0
Requires-Dist: urllib3 ==2.1.0
Requires-Dist: yarl ==1.9.3
